FrameDynamics/Block.py
FrameDynamics/Elements.py
FrameDynamics/Frame.py
FrameDynamics/Plotter.py
FrameDynamics/ShapeLoader.py
FrameDynamics/__init__.py
FrameDynamics-0.1.8.dist-info/LICENSE
FrameDynamics-0.1.8.dist-info/METADATA
FrameDynamics-0.1.8.dist-info/WHEEL
FrameDynamics-0.1.8.dist-info/top_level.txt
FrameDynamics-0.1.8.dist-info/RECORD
