Metadata-Version: 2.1
Name: FrameDynamics
Version: 0.1.8
Summary: Simulations of the average Hamiltonian.
Home-page: http://github.com/jdhaller/FrameDynamics
Author: Jens Daniel Haller
Author-email: jhaller@gmx.de
License: MIT
Keywords: NMR interaction average Hamiltonian theory toggling frame
Classifier: License :: OSI Approved :: MIT License
Classifier: Programming Language :: Python
Classifier: Topic :: Scientific/Engineering :: Physics
License-File: LICENSE
Requires-Dist: numpy
Requires-Dist: scipy (>=1.8.0)
Requires-Dist: matplotlib
